britishairways/__init__.py
britishairways/api.py
britishairways/ba_calendar.py
britishairways/ba_cheapest.py
britishairways/ba_graphs.py
britishairways/config.py
britishairways/data.py
britishairways/exceptions.py
britishairways/utils.py
tests/__init__.py
tests/test_api.py
tests/test_utils.py
britishairways-0.1.1.dist-info/LICENSE
britishairways-0.1.1.dist-info/METADATA
britishairways-0.1.1.dist-info/WHEEL
britishairways-0.1.1.dist-info/top_level.txt
britishairways-0.1.1.dist-info/RECORD
