Metadata-Version: 2.1
Name: britishairways
Version: 0.1.1
Summary: A Python package for fetching British Airways flight prices.
Home-page: https://github.com/alexechoi/british-airways-py
Author: Alex Choi
Author-email: alexchoidev@gmail.com
Classifier: Programming Language :: Python :: 3
Classifier: License :: OSI Approved :: MIT License
Classifier: Operating System :: OS Independent
Requires-Python: >=3.7
License-File: LICENSE
Requires-Dist: aiohttp>=3.8.0
